vibrary/__init__.py
vibrary-0.0.1.dist-info/METADATA
vibrary-0.0.1.dist-info/WHEEL
vibrary-0.0.1.dist-info/RECORD
