Metadata-Version: 2.4
Name: vibrary
Version: 0.0.1
Summary: Universal Content Registry for AI Applications - unified storage and semantic search for documents, posts, media
Project-URL: Homepage, https://github.com/LifeAiTools/vibrary
Project-URL: Documentation, https://github.com/LifeAiTools/vibrary#readme
Project-URL: Repository, https://github.com/LifeAiTools/vibrary
Project-URL: Issues, https://github.com/LifeAiTools/vibrary/issues
Author-email: LifeAiTools <dev@lifeaitools.com>
License-Expression: Apache-2.0
Keywords: ai,content-registry,document-management,hybrid-search,knowledge-base,qdrant,semantic-search,vector-search
Classifier: Development Status :: 1 - Planning
Classifier: Intended Audience :: Developers
Classifier: License :: OSI Approved :: Apache Software License
Classifier: Operating System :: OS Independent
Classifier: Programming Language :: Python :: 3
Classifier: Programming Language :: Python :: 3.10
Classifier: Programming Language :: Python :: 3.11
Classifier: Programming Language :: Python :: 3.12
Classifier: Topic :: Database
Classifier: Topic :: Scientific/Engineering :: Artificial Intelligence
Classifier: Topic :: Text Processing :: Indexing
Requires-Python: >=3.10
Provides-Extra: dev
Requires-Dist: pytest-asyncio>=0.21; extra == 'dev'
Requires-Dist: pytest>=7.0; extra == 'dev'
Requires-Dist: ruff>=0.1; extra == 'dev'
